payfast/__init__.py
payfast/api.py
payfast-0.1.4.dist-info/LICENSE
payfast-0.1.4.dist-info/METADATA
payfast-0.1.4.dist-info/WHEEL
payfast-0.1.4.dist-info/top_level.txt
payfast-0.1.4.dist-info/RECORD
