Metadata-Version: 2.1
Name: payfast
Version: 0.1.4
Summary: Python library for Payfast by network API
Home-page: https://github.com/intentio-software/payfast-python
Author: Max Dittmar
Author-email: Max Dittmar <max@intentio.co.za>
License: MIT License
Project-URL: Homepage, https://github.com/intentio-software/payfast-python
Classifier: Programming Language :: Python :: 3
Classifier: Development Status :: 3 - Alpha
License-File: LICENSE
Requires-Dist: requests >=2.0
Requires-Dist: pytz >=2021.1
Requires-Dist: pydantic <2.0,>=1.0
